setup.py
dhodistributions/Binomialdistribution.py
dhodistributions/Gaussiandistribution.py
dhodistributions/Generaldistribution.py
dhodistributions/__init__.py
dhodistributions.egg-info/PKG-INFO
dhodistributions.egg-info/SOURCES.txt
dhodistributions.egg-info/dependency_links.txt
dhodistributions.egg-info/not-zip-safe
dhodistributions.egg-info/top_level.txt