Metadata-Version: 1.0
Name: dhodistributions
Version: 1.1
Summary: Gaussian distributions
Home-page: UNKNOWN
Author: Dan Hernandez
Author-email: UNKNOWN
License: UNKNOWN
Platform: UNKNOWN
